{"loss": 22.416259765625, "time_this_iter_s": 23.926549911499023, "done": false, "timesteps_total": null, "episodes_total": null, "training_iteration": 1, "trial_id": "ba5ed_00436", "experiment_id": "a082c4a67b3b4881aef6796770906850", "date": "2022-12-09_17-27-07", "timestamp": 1670603227, "time_total_s": 23.926549911499023, "pid": 42084, "hostname": "MacBook-Pro-van-Sicco.local", "node_ip": "127.0.0.1", "config": {"horizon_size": 7, "horizon_list": [1, 2, 3, 4, 5, 6, 12], "quantile_size": 7, "tau_vec": [0.05, 0.1, 0.25, 0.5, 0.75, 0.9, 0.95], "columns": [1], "hidden_size": 12, "context_size": 4, "covariate_size": 3, "p1": 40, "initialization_prior": "Gaussian", "lr": 0.1, "layer_size": 1, "dropout": 0.0, "by_direction": false, "batch_size": 1, "num_epochs": 150, "early_validation_stopping": 8, "val_frac": 0.2, "load_stored_model": true, "store_results": true, "store_model": false, "dir_to_store_reg_quantiles": "s2s_results", "save_nn_name": "s2s_sim_exp2", "M": 10000, "m": 0, "sample_size": 150, "test_size": 200, "date": "221014", "seed": null, "device": "cpu"}, "time_since_restore": 23.926549911499023, "timesteps_since_restore": 0, "iterations_since_restore": 1, "warmup_time": 0.020693063735961914}
{"loss": 18.866415651688666, "time_this_iter_s": 0.012640953063964844, "done": false, "timesteps_total": null, "episodes_total": null, "training_iteration": 2, "trial_id": "ba5ed_00436", "experiment_id": "a082c4a67b3b4881aef6796770906850", "date": "2022-12-09_17-27-07", "timestamp": 1670603227, "time_total_s": 23.93919086456299, "pid": 42084, "hostname": "MacBook-Pro-van-Sicco.local", "node_ip": "127.0.0.1", "config": {"horizon_size": 7, "horizon_list": [1, 2, 3, 4, 5, 6, 12], "quantile_size": 7, "tau_vec": [0.05, 0.1, 0.25, 0.5, 0.75, 0.9, 0.95], "columns": [1], "hidden_size": 12, "context_size": 4, "covariate_size": 3, "p1": 40, "initialization_prior": "Gaussian", "lr": 0.1, "layer_size": 1, "dropout": 0.0, "by_direction": false, "batch_size": 1, "num_epochs": 150, "early_validation_stopping": 8, "val_frac": 0.2, "load_stored_model": true, "store_results": true, "store_model": false, "dir_to_store_reg_quantiles": "s2s_results", "save_nn_name": "s2s_sim_exp2", "M": 10000, "m": 0, "sample_size": 150, "test_size": 200, "date": "221014", "seed": null, "device": "cpu"}, "time_since_restore": 23.93919086456299, "timesteps_since_restore": 0, "iterations_since_restore": 2, "warmup_time": 0.020693063735961914}
{"loss": 16.17474858064829, "time_this_iter_s": 0.0034761428833007812, "done": false, "timesteps_total": null, "episodes_total": null, "training_iteration": 3, "trial_id": "ba5ed_00436", "experiment_id": "a082c4a67b3b4881aef6796770906850", "date": "2022-12-09_17-27-07", "timestamp": 1670603227, "time_total_s": 23.94266700744629, "pid": 42084, "hostname": "MacBook-Pro-van-Sicco.local", "node_ip": "127.0.0.1", "config": {"horizon_size": 7, "horizon_list": [1, 2, 3, 4, 5, 6, 12], "quantile_size": 7, "tau_vec": [0.05, 0.1, 0.25, 0.5, 0.75, 0.9, 0.95], "columns": [1], "hidden_size": 12, "context_size": 4, "covariate_size": 3, "p1": 40, "initialization_prior": "Gaussian", "lr": 0.1, "layer_size": 1, "dropout": 0.0, "by_direction": false, "batch_size": 1, "num_epochs": 150, "early_validation_stopping": 8, "val_frac": 0.2, "load_stored_model": true, "store_results": true, "store_model": false, "dir_to_store_reg_quantiles": "s2s_results", "save_nn_name": "s2s_sim_exp2", "M": 10000, "m": 0, "sample_size": 150, "test_size": 200, "date": "221014", "seed": null, "device": "cpu"}, "time_since_restore": 23.94266700744629, "timesteps_since_restore": 0, "iterations_since_restore": 3, "warmup_time": 0.020693063735961914}
{"loss": 13.9483028435559, "time_this_iter_s": 0.005909919738769531, "done": false, "timesteps_total": null, "episodes_total": null, "training_iteration": 4, "trial_id": "ba5ed_00436", "experiment_id": "a082c4a67b3b4881aef6796770906850", "date": "2022-12-09_17-27-07", "timestamp": 1670603227, "time_total_s": 23.94857692718506, "pid": 42084, "hostname": "MacBook-Pro-van-Sicco.local", "node_ip": "127.0.0.1", "config": {"horizon_size": 7, "horizon_list": [1, 2, 3, 4, 5, 6, 12], "quantile_size": 7, "tau_vec": [0.05, 0.1, 0.25, 0.5, 0.75, 0.9, 0.95], "columns": [1], "hidden_size": 12, "context_size": 4, "covariate_size": 3, "p1": 40, "initialization_prior": "Gaussian", "lr": 0.1, "layer_size": 1, "dropout": 0.0, "by_direction": false, "batch_size": 1, "num_epochs": 150, "early_validation_stopping": 8, "val_frac": 0.2, "load_stored_model": true, "store_results": true, "store_model": false, "dir_to_store_reg_quantiles": "s2s_results", "save_nn_name": "s2s_sim_exp2", "M": 10000, "m": 0, "sample_size": 150, "test_size": 200, "date": "221014", "seed": null, "device": "cpu"}, "time_since_restore": 23.94857692718506, "timesteps_since_restore": 0, "iterations_since_restore": 4, "warmup_time": 0.020693063735961914}
{"loss": 11.914664511354813, "time_this_iter_s": 0.004568815231323242, "done": false, "timesteps_total": null, "episodes_total": null, "training_iteration": 5, "trial_id": "ba5ed_00436", "experiment_id": "a082c4a67b3b4881aef6796770906850", "date": "2022-12-09_17-27-07", "timestamp": 1670603227, "time_total_s": 23.953145742416382, "pid": 42084, "hostname": "MacBook-Pro-van-Sicco.local", "node_ip": "127.0.0.1", "config": {"horizon_size": 7, "horizon_list": [1, 2, 3, 4, 5, 6, 12], "quantile_size": 7, "tau_vec": [0.05, 0.1, 0.25, 0.5, 0.75, 0.9, 0.95], "columns": [1], "hidden_size": 12, "context_size": 4, "covariate_size": 3, "p1": 40, "initialization_prior": "Gaussian", "lr": 0.1, "layer_size": 1, "dropout": 0.0, "by_direction": false, "batch_size": 1, "num_epochs": 150, "early_validation_stopping": 8, "val_frac": 0.2, "load_stored_model": true, "store_results": true, "store_model": false, "dir_to_store_reg_quantiles": "s2s_results", "save_nn_name": "s2s_sim_exp2", "M": 10000, "m": 0, "sample_size": 150, "test_size": 200, "date": "221014", "seed": null, "device": "cpu"}, "time_since_restore": 23.953145742416382, "timesteps_since_restore": 0, "iterations_since_restore": 5, "warmup_time": 0.020693063735961914}
{"loss": 9.973378057065217, "time_this_iter_s": 0.004576921463012695, "done": false, "timesteps_total": null, "episodes_total": null, "training_iteration": 6, "trial_id": "ba5ed_00436", "experiment_id": "a082c4a67b3b4881aef6796770906850", "date": "2022-12-09_17-27-07", "timestamp": 1670603227, "time_total_s": 23.957722663879395, "pid": 42084, "hostname": "MacBook-Pro-van-Sicco.local", "node_ip": "127.0.0.1", "config": {"horizon_size": 7, "horizon_list": [1, 2, 3, 4, 5, 6, 12], "quantile_size": 7, "tau_vec": [0.05, 0.1, 0.25, 0.5, 0.75, 0.9, 0.95], "columns": [1], "hidden_size": 12, "context_size": 4, "covariate_size": 3, "p1": 40, "initialization_prior": "Gaussian", "lr": 0.1, "layer_size": 1, "dropout": 0.0, "by_direction": false, "batch_size": 1, "num_epochs": 150, "early_validation_stopping": 8, "val_frac": 0.2, "load_stored_model": true, "store_results": true, "store_model": false, "dir_to_store_reg_quantiles": "s2s_results", "save_nn_name": "s2s_sim_exp2", "M": 10000, "m": 0, "sample_size": 150, "test_size": 200, "date": "221014", "seed": null, "device": "cpu"}, "time_since_restore": 23.957722663879395, "timesteps_since_restore": 0, "iterations_since_restore": 6, "warmup_time": 0.020693063735961914}
{"loss": 8.27360278775233, "time_this_iter_s": 0.005740165710449219, "done": false, "timesteps_total": null, "episodes_total": null, "training_iteration": 7, "trial_id": "ba5ed_00436", "experiment_id": "a082c4a67b3b4881aef6796770906850", "date": "2022-12-09_17-27-07", "timestamp": 1670603227, "time_total_s": 23.963462829589844, "pid": 42084, "hostname": "MacBook-Pro-van-Sicco.local", "node_ip": "127.0.0.1", "config": {"horizon_size": 7, "horizon_list": [1, 2, 3, 4, 5, 6, 12], "quantile_size": 7, "tau_vec": [0.05, 0.1, 0.25, 0.5, 0.75, 0.9, 0.95], "columns": [1], "hidden_size": 12, "context_size": 4, "covariate_size": 3, "p1": 40, "initialization_prior": "Gaussian", "lr": 0.1, "layer_size": 1, "dropout": 0.0, "by_direction": false, "batch_size": 1, "num_epochs": 150, "early_validation_stopping": 8, "val_frac": 0.2, "load_stored_model": true, "store_results": true, "store_model": false, "dir_to_store_reg_quantiles": "s2s_results", "save_nn_name": "s2s_sim_exp2", "M": 10000, "m": 0, "sample_size": 150, "test_size": 200, "date": "221014", "seed": null, "device": "cpu"}, "time_since_restore": 23.963462829589844, "timesteps_since_restore": 0, "iterations_since_restore": 7, "warmup_time": 0.020693063735961914}
{"loss": 6.96848159695264, "time_this_iter_s": 0.0048828125, "done": false, "timesteps_total": null, "episodes_total": null, "training_iteration": 8, "trial_id": "ba5ed_00436", "experiment_id": "a082c4a67b3b4881aef6796770906850", "date": "2022-12-09_17-27-07", "timestamp": 1670603227, "time_total_s": 23.968345642089844, "pid": 42084, "hostname": "MacBook-Pro-van-Sicco.local", "node_ip": "127.0.0.1", "config": {"horizon_size": 7, "horizon_list": [1, 2, 3, 4, 5, 6, 12], "quantile_size": 7, "tau_vec": [0.05, 0.1, 0.25, 0.5, 0.75, 0.9, 0.95], "columns": [1], "hidden_size": 12, "context_size": 4, "covariate_size": 3, "p1": 40, "initialization_prior": "Gaussian", "lr": 0.1, "layer_size": 1, "dropout": 0.0, "by_direction": false, "batch_size": 1, "num_epochs": 150, "early_validation_stopping": 8, "val_frac": 0.2, "load_stored_model": true, "store_results": true, "store_model": false, "dir_to_store_reg_quantiles": "s2s_results", "save_nn_name": "s2s_sim_exp2", "M": 10000, "m": 0, "sample_size": 150, "test_size": 200, "date": "221014", "seed": null, "device": "cpu"}, "time_since_restore": 23.968345642089844, "timesteps_since_restore": 0, "iterations_since_restore": 8, "warmup_time": 0.020693063735961914}
{"loss": 5.935247385723991, "time_this_iter_s": 0.004872322082519531, "done": false, "timesteps_total": null, "episodes_total": null, "training_iteration": 9, "trial_id": "ba5ed_00436", "experiment_id": "a082c4a67b3b4881aef6796770906850", "date": "2022-12-09_17-27-07", "timestamp": 1670603227, "time_total_s": 23.973217964172363, "pid": 42084, "hostname": "MacBook-Pro-van-Sicco.local", "node_ip": "127.0.0.1", "config": {"horizon_size": 7, "horizon_list": [1, 2, 3, 4, 5, 6, 12], "quantile_size": 7, "tau_vec": [0.05, 0.1, 0.25, 0.5, 0.75, 0.9, 0.95], "columns": [1], "hidden_size": 12, "context_size": 4, "covariate_size": 3, "p1": 40, "initialization_prior": "Gaussian", "lr": 0.1, "layer_size": 1, "dropout": 0.0, "by_direction": false, "batch_size": 1, "num_epochs": 150, "early_validation_stopping": 8, "val_frac": 0.2, "load_stored_model": true, "store_results": true, "store_model": false, "dir_to_store_reg_quantiles": "s2s_results", "save_nn_name": "s2s_sim_exp2", "M": 10000, "m": 0, "sample_size": 150, "test_size": 200, "date": "221014", "seed": null, "device": "cpu"}, "time_since_restore": 23.973217964172363, "timesteps_since_restore": 0, "iterations_since_restore": 9, "warmup_time": 0.020693063735961914}
{"loss": 5.083485478940218, "time_this_iter_s": 0.005241870880126953, "done": false, "timesteps_total": null, "episodes_total": null, "training_iteration": 10, "trial_id": "ba5ed_00436", "experiment_id": "a082c4a67b3b4881aef6796770906850", "date": "2022-12-09_17-27-07", "timestamp": 1670603227, "time_total_s": 23.97845983505249, "pid": 42084, "hostname": "MacBook-Pro-van-Sicco.local", "node_ip": "127.0.0.1", "config": {"horizon_size": 7, "horizon_list": [1, 2, 3, 4, 5, 6, 12], "quantile_size": 7, "tau_vec": [0.05, 0.1, 0.25, 0.5, 0.75, 0.9, 0.95], "columns": [1], "hidden_size": 12, "context_size": 4, "covariate_size": 3, "p1": 40, "initialization_prior": "Gaussian", "lr": 0.1, "layer_size": 1, "dropout": 0.0, "by_direction": false, "batch_size": 1, "num_epochs": 150, "early_validation_stopping": 8, "val_frac": 0.2, "load_stored_model": true, "store_results": true, "store_model": false, "dir_to_store_reg_quantiles": "s2s_results", "save_nn_name": "s2s_sim_exp2", "M": 10000, "m": 0, "sample_size": 150, "test_size": 200, "date": "221014", "seed": null, "device": "cpu"}, "time_since_restore": 23.97845983505249, "timesteps_since_restore": 0, "iterations_since_restore": 10, "warmup_time": 0.020693063735961914}
{"loss": 4.329918902853261, "time_this_iter_s": 0.005383968353271484, "done": false, "timesteps_total": null, "episodes_total": null, "training_iteration": 11, "trial_id": "ba5ed_00436", "experiment_id": "a082c4a67b3b4881aef6796770906850", "date": "2022-12-09_17-27-07", "timestamp": 1670603227, "time_total_s": 23.98384380340576, "pid": 42084, "hostname": "MacBook-Pro-van-Sicco.local", "node_ip": "127.0.0.1", "config": {"horizon_size": 7, "horizon_list": [1, 2, 3, 4, 5, 6, 12], "quantile_size": 7, "tau_vec": [0.05, 0.1, 0.25, 0.5, 0.75, 0.9, 0.95], "columns": [1], "hidden_size": 12, "context_size": 4, "covariate_size": 3, "p1": 40, "initialization_prior": "Gaussian", "lr": 0.1, "layer_size": 1, "dropout": 0.0, "by_direction": false, "batch_size": 1, "num_epochs": 150, "early_validation_stopping": 8, "val_frac": 0.2, "load_stored_model": true, "store_results": true, "store_model": false, "dir_to_store_reg_quantiles": "s2s_results", "save_nn_name": "s2s_sim_exp2", "M": 10000, "m": 0, "sample_size": 150, "test_size": 200, "date": "221014", "seed": null, "device": "cpu"}, "time_since_restore": 23.98384380340576, "timesteps_since_restore": 0, "iterations_since_restore": 11, "warmup_time": 0.020693063735961914}
{"loss": 3.736330778702446, "time_this_iter_s": 0.00452113151550293, "done": false, "timesteps_total": null, "episodes_total": null, "training_iteration": 12, "trial_id": "ba5ed_00436", "experiment_id": "a082c4a67b3b4881aef6796770906850", "date": "2022-12-09_17-27-07", "timestamp": 1670603227, "time_total_s": 23.988364934921265, "pid": 42084, "hostname": "MacBook-Pro-van-Sicco.local", "node_ip": "127.0.0.1", "config": {"horizon_size": 7, "horizon_list": [1, 2, 3, 4, 5, 6, 12], "quantile_size": 7, "tau_vec": [0.05, 0.1, 0.25, 0.5, 0.75, 0.9, 0.95], "columns": [1], "hidden_size": 12, "context_size": 4, "covariate_size": 3, "p1": 40, "initialization_prior": "Gaussian", "lr": 0.1, "layer_size": 1, "dropout": 0.0, "by_direction": false, "batch_size": 1, "num_epochs": 150, "early_validation_stopping": 8, "val_frac": 0.2, "load_stored_model": true, "store_results": true, "store_model": false, "dir_to_store_reg_quantiles": "s2s_results", "save_nn_name": "s2s_sim_exp2", "M": 10000, "m": 0, "sample_size": 150, "test_size": 200, "date": "221014", "seed": null, "device": "cpu"}, "time_since_restore": 23.988364934921265, "timesteps_since_restore": 0, "iterations_since_restore": 12, "warmup_time": 0.020693063735961914}
{"loss": 3.3580750649019797, "time_this_iter_s": 0.005436897277832031, "done": false, "timesteps_total": null, "episodes_total": null, "training_iteration": 13, "trial_id": "ba5ed_00436", "experiment_id": "a082c4a67b3b4881aef6796770906850", "date": "2022-12-09_17-27-07", "timestamp": 1670603227, "time_total_s": 23.993801832199097, "pid": 42084, "hostname": "MacBook-Pro-van-Sicco.local", "node_ip": "127.0.0.1", "config": {"horizon_size": 7, "horizon_list": [1, 2, 3, 4, 5, 6, 12], "quantile_size": 7, "tau_vec": [0.05, 0.1, 0.25, 0.5, 0.75, 0.9, 0.95], "columns": [1], "hidden_size": 12, "context_size": 4, "covariate_size": 3, "p1": 40, "initialization_prior": "Gaussian", "lr": 0.1, "layer_size": 1, "dropout": 0.0, "by_direction": false, "batch_size": 1, "num_epochs": 150, "early_validation_stopping": 8, "val_frac": 0.2, "load_stored_model": true, "store_results": true, "store_model": false, "dir_to_store_reg_quantiles": "s2s_results", "save_nn_name": "s2s_sim_exp2", "M": 10000, "m": 0, "sample_size": 150, "test_size": 200, "date": "221014", "seed": null, "device": "cpu"}, "time_since_restore": 23.993801832199097, "timesteps_since_restore": 0, "iterations_since_restore": 13, "warmup_time": 0.020693063735961914}
{"loss": 3.0519811026057844, "time_this_iter_s": 0.006574153900146484, "done": false, "timesteps_total": null, "episodes_total": null, "training_iteration": 14, "trial_id": "ba5ed_00436", "experiment_id": "a082c4a67b3b4881aef6796770906850", "date": "2022-12-09_17-27-07", "timestamp": 1670603227, "time_total_s": 24.000375986099243, "pid": 42084, "hostname": "MacBook-Pro-van-Sicco.local", "node_ip": "127.0.0.1", "config": {"horizon_size": 7, "horizon_list": [1, 2, 3, 4, 5, 6, 12], "quantile_size": 7, "tau_vec": [0.05, 0.1, 0.25, 0.5, 0.75, 0.9, 0.95], "columns": [1], "hidden_size": 12, "context_size": 4, "covariate_size": 3, "p1": 40, "initialization_prior": "Gaussian", "lr": 0.1, "layer_size": 1, "dropout": 0.0, "by_direction": false, "batch_size": 1, "num_epochs": 150, "early_validation_stopping": 8, "val_frac": 0.2, "load_stored_model": true, "store_results": true, "store_model": false, "dir_to_store_reg_quantiles": "s2s_results", "save_nn_name": "s2s_sim_exp2", "M": 10000, "m": 0, "sample_size": 150, "test_size": 200, "date": "221014", "seed": null, "device": "cpu"}, "time_since_restore": 24.000375986099243, "timesteps_since_restore": 0, "iterations_since_restore": 14, "warmup_time": 0.020693063735961914}
{"loss": 2.866391389266304, "time_this_iter_s": 0.005411863327026367, "done": false, "timesteps_total": null, "episodes_total": null, "training_iteration": 15, "trial_id": "ba5ed_00436", "experiment_id": "a082c4a67b3b4881aef6796770906850", "date": "2022-12-09_17-27-07", "timestamp": 1670603227, "time_total_s": 24.00578784942627, "pid": 42084, "hostname": "MacBook-Pro-van-Sicco.local", "node_ip": "127.0.0.1", "config": {"horizon_size": 7, "horizon_list": [1, 2, 3, 4, 5, 6, 12], "quantile_size": 7, "tau_vec": [0.05, 0.1, 0.25, 0.5, 0.75, 0.9, 0.95], "columns": [1], "hidden_size": 12, "context_size": 4, "covariate_size": 3, "p1": 40, "initialization_prior": "Gaussian", "lr": 0.1, "layer_size": 1, "dropout": 0.0, "by_direction": false, "batch_size": 1, "num_epochs": 150, "early_validation_stopping": 8, "val_frac": 0.2, "load_stored_model": true, "store_results": true, "store_model": false, "dir_to_store_reg_quantiles": "s2s_results", "save_nn_name": "s2s_sim_exp2", "M": 10000, "m": 0, "sample_size": 150, "test_size": 200, "date": "221014", "seed": null, "device": "cpu"}, "time_since_restore": 24.00578784942627, "timesteps_since_restore": 0, "iterations_since_restore": 15, "warmup_time": 0.020693063735961914}
{"loss": 2.7139684072932844, "time_this_iter_s": 0.004930019378662109, "done": false, "timesteps_total": null, "episodes_total": null, "training_iteration": 16, "trial_id": "ba5ed_00436", "experiment_id": "a082c4a67b3b4881aef6796770906850", "date": "2022-12-09_17-27-07", "timestamp": 1670603227, "time_total_s": 24.01071786880493, "pid": 42084, "hostname": "MacBook-Pro-van-Sicco.local", "node_ip": "127.0.0.1", "config": {"horizon_size": 7, "horizon_list": [1, 2, 3, 4, 5, 6, 12], "quantile_size": 7, "tau_vec": [0.05, 0.1, 0.25, 0.5, 0.75, 0.9, 0.95], "columns": [1], "hidden_size": 12, "context_size": 4, "covariate_size": 3, "p1": 40, "initialization_prior": "Gaussian", "lr": 0.1, "layer_size": 1, "dropout": 0.0, "by_direction": false, "batch_size": 1, "num_epochs": 150, "early_validation_stopping": 8, "val_frac": 0.2, "load_stored_model": true, "store_results": true, "store_model": false, "dir_to_store_reg_quantiles": "s2s_results", "save_nn_name": "s2s_sim_exp2", "M": 10000, "m": 0, "sample_size": 150, "test_size": 200, "date": "221014", "seed": null, "device": "cpu"}, "time_since_restore": 24.01071786880493, "timesteps_since_restore": 0, "iterations_since_restore": 16, "warmup_time": 0.020693063735961914}
{"loss": 2.5668289468895575, "time_this_iter_s": 0.0057179927825927734, "done": false, "timesteps_total": null, "episodes_total": null, "training_iteration": 17, "trial_id": "ba5ed_00436", "experiment_id": "a082c4a67b3b4881aef6796770906850", "date": "2022-12-09_17-27-07", "timestamp": 1670603227, "time_total_s": 24.016435861587524, "pid": 42084, "hostname": "MacBook-Pro-van-Sicco.local", "node_ip": "127.0.0.1", "config": {"horizon_size": 7, "horizon_list": [1, 2, 3, 4, 5, 6, 12], "quantile_size": 7, "tau_vec": [0.05, 0.1, 0.25, 0.5, 0.75, 0.9, 0.95], "columns": [1], "hidden_size": 12, "context_size": 4, "covariate_size": 3, "p1": 40, "initialization_prior": "Gaussian", "lr": 0.1, "layer_size": 1, "dropout": 0.0, "by_direction": false, "batch_size": 1, "num_epochs": 150, "early_validation_stopping": 8, "val_frac": 0.2, "load_stored_model": true, "store_results": true, "store_model": false, "dir_to_store_reg_quantiles": "s2s_results", "save_nn_name": "s2s_sim_exp2", "M": 10000, "m": 0, "sample_size": 150, "test_size": 200, "date": "221014", "seed": null, "device": "cpu"}, "time_since_restore": 24.016435861587524, "timesteps_since_restore": 0, "iterations_since_restore": 17, "warmup_time": 0.020693063735961914}
{"loss": 2.4626146399456523, "time_this_iter_s": 0.004662990570068359, "done": false, "timesteps_total": null, "episodes_total": null, "training_iteration": 18, "trial_id": "ba5ed_00436", "experiment_id": "a082c4a67b3b4881aef6796770906850", "date": "2022-12-09_17-27-07", "timestamp": 1670603227, "time_total_s": 24.021098852157593, "pid": 42084, "hostname": "MacBook-Pro-van-Sicco.local", "node_ip": "127.0.0.1", "config": {"horizon_size": 7, "horizon_list": [1, 2, 3, 4, 5, 6, 12], "quantile_size": 7, "tau_vec": [0.05, 0.1, 0.25, 0.5, 0.75, 0.9, 0.95], "columns": [1], "hidden_size": 12, "context_size": 4, "covariate_size": 3, "p1": 40, "initialization_prior": "Gaussian", "lr": 0.1, "layer_size": 1, "dropout": 0.0, "by_direction": false, "batch_size": 1, "num_epochs": 150, "early_validation_stopping": 8, "val_frac": 0.2, "load_stored_model": true, "store_results": true, "store_model": false, "dir_to_store_reg_quantiles": "s2s_results", "save_nn_name": "s2s_sim_exp2", "M": 10000, "m": 0, "sample_size": 150, "test_size": 200, "date": "221014", "seed": null, "device": "cpu"}, "time_since_restore": 24.021098852157593, "timesteps_since_restore": 0, "iterations_since_restore": 18, "warmup_time": 0.020693063735961914}
{"loss": 2.366763855359569, "time_this_iter_s": 0.0046710968017578125, "done": false, "timesteps_total": null, "episodes_total": null, "training_iteration": 19, "trial_id": "ba5ed_00436", "experiment_id": "a082c4a67b3b4881aef6796770906850", "date": "2022-12-09_17-27-07", "timestamp": 1670603227, "time_total_s": 24.02576994895935, "pid": 42084, "hostname": "MacBook-Pro-van-Sicco.local", "node_ip": "127.0.0.1", "config": {"horizon_size": 7, "horizon_list": [1, 2, 3, 4, 5, 6, 12], "quantile_size": 7, "tau_vec": [0.05, 0.1, 0.25, 0.5, 0.75, 0.9, 0.95], "columns": [1], "hidden_size": 12, "context_size": 4, "covariate_size": 3, "p1": 40, "initialization_prior": "Gaussian", "lr": 0.1, "layer_size": 1, "dropout": 0.0, "by_direction": false, "batch_size": 1, "num_epochs": 150, "early_validation_stopping": 8, "val_frac": 0.2, "load_stored_model": true, "store_results": true, "store_model": false, "dir_to_store_reg_quantiles": "s2s_results", "save_nn_name": "s2s_sim_exp2", "M": 10000, "m": 0, "sample_size": 150, "test_size": 200, "date": "221014", "seed": null, "device": "cpu"}, "time_since_restore": 24.02576994895935, "timesteps_since_restore": 0, "iterations_since_restore": 19, "warmup_time": 0.020693063735961914}
{"loss": 2.283988052273389, "time_this_iter_s": 0.00598597526550293, "done": false, "timesteps_total": null, "episodes_total": null, "training_iteration": 20, "trial_id": "ba5ed_00436", "experiment_id": "a082c4a67b3b4881aef6796770906850", "date": "2022-12-09_17-27-07", "timestamp": 1670603227, "time_total_s": 24.031755924224854, "pid": 42084, "hostname": "MacBook-Pro-van-Sicco.local", "node_ip": "127.0.0.1", "config": {"horizon_size": 7, "horizon_list": [1, 2, 3, 4, 5, 6, 12], "quantile_size": 7, "tau_vec": [0.05, 0.1, 0.25, 0.5, 0.75, 0.9, 0.95], "columns": [1], "hidden_size": 12, "context_size": 4, "covariate_size": 3, "p1": 40, "initialization_prior": "Gaussian", "lr": 0.1, "layer_size": 1, "dropout": 0.0, "by_direction": false, "batch_size": 1, "num_epochs": 150, "early_validation_stopping": 8, "val_frac": 0.2, "load_stored_model": true, "store_results": true, "store_model": false, "dir_to_store_reg_quantiles": "s2s_results", "save_nn_name": "s2s_sim_exp2", "M": 10000, "m": 0, "sample_size": 150, "test_size": 200, "date": "221014", "seed": null, "device": "cpu"}, "time_since_restore": 24.031755924224854, "timesteps_since_restore": 0, "iterations_since_restore": 20, "warmup_time": 0.020693063735961914}
{"loss": 2.200077980941867, "time_this_iter_s": 0.004718780517578125, "done": false, "timesteps_total": null, "episodes_total": null, "training_iteration": 21, "trial_id": "ba5ed_00436", "experiment_id": "a082c4a67b3b4881aef6796770906850", "date": "2022-12-09_17-27-07", "timestamp": 1670603227, "time_total_s": 24.03647470474243, "pid": 42084, "hostname": "MacBook-Pro-van-Sicco.local", "node_ip": "127.0.0.1", "config": {"horizon_size": 7, "horizon_list": [1, 2, 3, 4, 5, 6, 12], "quantile_size": 7, "tau_vec": [0.05, 0.1, 0.25, 0.5, 0.75, 0.9, 0.95], "columns": [1], "hidden_size": 12, "context_size": 4, "covariate_size": 3, "p1": 40, "initialization_prior": "Gaussian", "lr": 0.1, "layer_size": 1, "dropout": 0.0, "by_direction": false, "batch_size": 1, "num_epochs": 150, "early_validation_stopping": 8, "val_frac": 0.2, "load_stored_model": true, "store_results": true, "store_model": false, "dir_to_store_reg_quantiles": "s2s_results", "save_nn_name": "s2s_sim_exp2", "M": 10000, "m": 0, "sample_size": 150, "test_size": 200, "date": "221014", "seed": null, "device": "cpu"}, "time_since_restore": 24.03647470474243, "timesteps_since_restore": 0, "iterations_since_restore": 21, "warmup_time": 0.020693063735961914}
{"loss": 2.118884921814344, "time_this_iter_s": 0.004564046859741211, "done": false, "timesteps_total": null, "episodes_total": null, "training_iteration": 22, "trial_id": "ba5ed_00436", "experiment_id": "a082c4a67b3b4881aef6796770906850", "date": "2022-12-09_17-27-07", "timestamp": 1670603227, "time_total_s": 24.041038751602173, "pid": 42084, "hostname": "MacBook-Pro-van-Sicco.local", "node_ip": "127.0.0.1", "config": {"horizon_size": 7, "horizon_list": [1, 2, 3, 4, 5, 6, 12], "quantile_size": 7, "tau_vec": [0.05, 0.1, 0.25, 0.5, 0.75, 0.9, 0.95], "columns": [1], "hidden_size": 12, "context_size": 4, "covariate_size": 3, "p1": 40, "initialization_prior": "Gaussian", "lr": 0.1, "layer_size": 1, "dropout": 0.0, "by_direction": false, "batch_size": 1, "num_epochs": 150, "early_validation_stopping": 8, "val_frac": 0.2, "load_stored_model": true, "store_results": true, "store_model": false, "dir_to_store_reg_quantiles": "s2s_results", "save_nn_name": "s2s_sim_exp2", "M": 10000, "m": 0, "sample_size": 150, "test_size": 200, "date": "221014", "seed": null, "device": "cpu"}, "time_since_restore": 24.041038751602173, "timesteps_since_restore": 0, "iterations_since_restore": 22, "warmup_time": 0.020693063735961914}
{"loss": 2.0488010193250195, "time_this_iter_s": 0.004947185516357422, "done": false, "timesteps_total": null, "episodes_total": null, "training_iteration": 23, "trial_id": "ba5ed_00436", "experiment_id": "a082c4a67b3b4881aef6796770906850", "date": "2022-12-09_17-27-07", "timestamp": 1670603227, "time_total_s": 24.04598593711853, "pid": 42084, "hostname": "MacBook-Pro-van-Sicco.local", "node_ip": "127.0.0.1", "config": {"horizon_size": 7, "horizon_list": [1, 2, 3, 4, 5, 6, 12], "quantile_size": 7, "tau_vec": [0.05, 0.1, 0.25, 0.5, 0.75, 0.9, 0.95], "columns": [1], "hidden_size": 12, "context_size": 4, "covariate_size": 3, "p1": 40, "initialization_prior": "Gaussian", "lr": 0.1, "layer_size": 1, "dropout": 0.0, "by_direction": false, "batch_size": 1, "num_epochs": 150, "early_validation_stopping": 8, "val_frac": 0.2, "load_stored_model": true, "store_results": true, "store_model": false, "dir_to_store_reg_quantiles": "s2s_results", "save_nn_name": "s2s_sim_exp2", "M": 10000, "m": 0, "sample_size": 150, "test_size": 200, "date": "221014", "seed": null, "device": "cpu"}, "time_since_restore": 24.04598593711853, "timesteps_since_restore": 0, "iterations_since_restore": 23, "warmup_time": 0.020693063735961914}
{"loss": 1.9822956345836569, "time_this_iter_s": 0.00488591194152832, "done": false, "timesteps_total": null, "episodes_total": null, "training_iteration": 24, "trial_id": "ba5ed_00436", "experiment_id": "a082c4a67b3b4881aef6796770906850", "date": "2022-12-09_17-27-07", "timestamp": 1670603227, "time_total_s": 24.05087184906006, "pid": 42084, "hostname": "MacBook-Pro-van-Sicco.local", "node_ip": "127.0.0.1", "config": {"horizon_size": 7, "horizon_list": [1, 2, 3, 4, 5, 6, 12], "quantile_size": 7, "tau_vec": [0.05, 0.1, 0.25, 0.5, 0.75, 0.9, 0.95], "columns": [1], "hidden_size": 12, "context_size": 4, "covariate_size": 3, "p1": 40, "initialization_prior": "Gaussian", "lr": 0.1, "layer_size": 1, "dropout": 0.0, "by_direction": false, "batch_size": 1, "num_epochs": 150, "early_validation_stopping": 8, "val_frac": 0.2, "load_stored_model": true, "store_results": true, "store_model": false, "dir_to_store_reg_quantiles": "s2s_results", "save_nn_name": "s2s_sim_exp2", "M": 10000, "m": 0, "sample_size": 150, "test_size": 200, "date": "221014", "seed": null, "device": "cpu"}, "time_since_restore": 24.05087184906006, "timesteps_since_restore": 0, "iterations_since_restore": 24, "warmup_time": 0.020693063735961914}
{"loss": 1.9364152043502523, "time_this_iter_s": 0.003993988037109375, "done": false, "timesteps_total": null, "episodes_total": null, "training_iteration": 25, "trial_id": "ba5ed_00436", "experiment_id": "a082c4a67b3b4881aef6796770906850", "date": "2022-12-09_17-27-07", "timestamp": 1670603227, "time_total_s": 24.054865837097168, "pid": 42084, "hostname": "MacBook-Pro-van-Sicco.local", "node_ip": "127.0.0.1", "config": {"horizon_size": 7, "horizon_list": [1, 2, 3, 4, 5, 6, 12], "quantile_size": 7, "tau_vec": [0.05, 0.1, 0.25, 0.5, 0.75, 0.9, 0.95], "columns": [1], "hidden_size": 12, "context_size": 4, "covariate_size": 3, "p1": 40, "initialization_prior": "Gaussian", "lr": 0.1, "layer_size": 1, "dropout": 0.0, "by_direction": false, "batch_size": 1, "num_epochs": 150, "early_validation_stopping": 8, "val_frac": 0.2, "load_stored_model": true, "store_results": true, "store_model": false, "dir_to_store_reg_quantiles": "s2s_results", "save_nn_name": "s2s_sim_exp2", "M": 10000, "m": 0, "sample_size": 150, "test_size": 200, "date": "221014", "seed": null, "device": "cpu"}, "time_since_restore": 24.054865837097168, "timesteps_since_restore": 0, "iterations_since_restore": 25, "warmup_time": 0.020693063735961914}
{"loss": 1.9083492681846856, "time_this_iter_s": 0.005381107330322266, "done": false, "timesteps_total": null, "episodes_total": null, "training_iteration": 26, "trial_id": "ba5ed_00436", "experiment_id": "a082c4a67b3b4881aef6796770906850", "date": "2022-12-09_17-27-07", "timestamp": 1670603227, "time_total_s": 24.06024694442749, "pid": 42084, "hostname": "MacBook-Pro-van-Sicco.local", "node_ip": "127.0.0.1", "config": {"horizon_size": 7, "horizon_list": [1, 2, 3, 4, 5, 6, 12], "quantile_size": 7, "tau_vec": [0.05, 0.1, 0.25, 0.5, 0.75, 0.9, 0.95], "columns": [1], "hidden_size": 12, "context_size": 4, "covariate_size": 3, "p1": 40, "initialization_prior": "Gaussian", "lr": 0.1, "layer_size": 1, "dropout": 0.0, "by_direction": false, "batch_size": 1, "num_epochs": 150, "early_validation_stopping": 8, "val_frac": 0.2, "load_stored_model": true, "store_results": true, "store_model": false, "dir_to_store_reg_quantiles": "s2s_results", "save_nn_name": "s2s_sim_exp2", "M": 10000, "m": 0, "sample_size": 150, "test_size": 200, "date": "221014", "seed": null, "device": "cpu"}, "time_since_restore": 24.06024694442749, "timesteps_since_restore": 0, "iterations_since_restore": 26, "warmup_time": 0.020693063735961914}
{"loss": 1.9001948196695457, "time_this_iter_s": 0.004797935485839844, "done": false, "timesteps_total": null, "episodes_total": null, "training_iteration": 27, "trial_id": "ba5ed_00436", "experiment_id": "a082c4a67b3b4881aef6796770906850", "date": "2022-12-09_17-27-07", "timestamp": 1670603227, "time_total_s": 24.06504487991333, "pid": 42084, "hostname": "MacBook-Pro-van-Sicco.local", "node_ip": "127.0.0.1", "config": {"horizon_size": 7, "horizon_list": [1, 2, 3, 4, 5, 6, 12], "quantile_size": 7, "tau_vec": [0.05, 0.1, 0.25, 0.5, 0.75, 0.9, 0.95], "columns": [1], "hidden_size": 12, "context_size": 4, "covariate_size": 3, "p1": 40, "initialization_prior": "Gaussian", "lr": 0.1, "layer_size": 1, "dropout": 0.0, "by_direction": false, "batch_size": 1, "num_epochs": 150, "early_validation_stopping": 8, "val_frac": 0.2, "load_stored_model": true, "store_results": true, "store_model": false, "dir_to_store_reg_quantiles": "s2s_results", "save_nn_name": "s2s_sim_exp2", "M": 10000, "m": 0, "sample_size": 150, "test_size": 200, "date": "221014", "seed": null, "device": "cpu"}, "time_since_restore": 24.06504487991333, "timesteps_since_restore": 0, "iterations_since_restore": 27, "warmup_time": 0.020693063735961914}
{"loss": 1.8656525226853649, "time_this_iter_s": 0.004864931106567383, "done": false, "timesteps_total": null, "episodes_total": null, "training_iteration": 28, "trial_id": "ba5ed_00436", "experiment_id": "a082c4a67b3b4881aef6796770906850", "date": "2022-12-09_17-27-07", "timestamp": 1670603227, "time_total_s": 24.069909811019897, "pid": 42084, "hostname": "MacBook-Pro-van-Sicco.local", "node_ip": "127.0.0.1", "config": {"horizon_size": 7, "horizon_list": [1, 2, 3, 4, 5, 6, 12], "quantile_size": 7, "tau_vec": [0.05, 0.1, 0.25, 0.5, 0.75, 0.9, 0.95], "columns": [1], "hidden_size": 12, "context_size": 4, "covariate_size": 3, "p1": 40, "initialization_prior": "Gaussian", "lr": 0.1, "layer_size": 1, "dropout": 0.0, "by_direction": false, "batch_size": 1, "num_epochs": 150, "early_validation_stopping": 8, "val_frac": 0.2, "load_stored_model": true, "store_results": true, "store_model": false, "dir_to_store_reg_quantiles": "s2s_results", "save_nn_name": "s2s_sim_exp2", "M": 10000, "m": 0, "sample_size": 150, "test_size": 200, "date": "221014", "seed": null, "device": "cpu"}, "time_since_restore": 24.069909811019897, "timesteps_since_restore": 0, "iterations_since_restore": 28, "warmup_time": 0.020693063735961914}
{"loss": 1.8465843437621312, "time_this_iter_s": 0.0033838748931884766, "done": false, "timesteps_total": null, "episodes_total": null, "training_iteration": 29, "trial_id": "ba5ed_00436", "experiment_id": "a082c4a67b3b4881aef6796770906850", "date": "2022-12-09_17-27-07", "timestamp": 1670603227, "time_total_s": 24.073293685913086, "pid": 42084, "hostname": "MacBook-Pro-van-Sicco.local", "node_ip": "127.0.0.1", "config": {"horizon_size": 7, "horizon_list": [1, 2, 3, 4, 5, 6, 12], "quantile_size": 7, "tau_vec": [0.05, 0.1, 0.25, 0.5, 0.75, 0.9, 0.95], "columns": [1], "hidden_size": 12, "context_size": 4, "covariate_size": 3, "p1": 40, "initialization_prior": "Gaussian", "lr": 0.1, "layer_size": 1, "dropout": 0.0, "by_direction": false, "batch_size": 1, "num_epochs": 150, "early_validation_stopping": 8, "val_frac": 0.2, "load_stored_model": true, "store_results": true, "store_model": false, "dir_to_store_reg_quantiles": "s2s_results", "save_nn_name": "s2s_sim_exp2", "M": 10000, "m": 0, "sample_size": 150, "test_size": 200, "date": "221014", "seed": null, "device": "cpu"}, "time_since_restore": 24.073293685913086, "timesteps_since_restore": 0, "iterations_since_restore": 29, "warmup_time": 0.020693063735961914}
{"loss": 1.8162519561578028, "time_this_iter_s": 0.006031036376953125, "done": false, "timesteps_total": null, "episodes_total": null, "training_iteration": 30, "trial_id": "ba5ed_00436", "experiment_id": "a082c4a67b3b4881aef6796770906850", "date": "2022-12-09_17-27-07", "timestamp": 1670603227, "time_total_s": 24.07932472229004, "pid": 42084, "hostname": "MacBook-Pro-van-Sicco.local", "node_ip": "127.0.0.1", "config": {"horizon_size": 7, "horizon_list": [1, 2, 3, 4, 5, 6, 12], "quantile_size": 7, "tau_vec": [0.05, 0.1, 0.25, 0.5, 0.75, 0.9, 0.95], "columns": [1], "hidden_size": 12, "context_size": 4, "covariate_size": 3, "p1": 40, "initialization_prior": "Gaussian", "lr": 0.1, "layer_size": 1, "dropout": 0.0, "by_direction": false, "batch_size": 1, "num_epochs": 150, "early_validation_stopping": 8, "val_frac": 0.2, "load_stored_model": true, "store_results": true, "store_model": false, "dir_to_store_reg_quantiles": "s2s_results", "save_nn_name": "s2s_sim_exp2", "M": 10000, "m": 0, "sample_size": 150, "test_size": 200, "date": "221014", "seed": null, "device": "cpu"}, "time_since_restore": 24.07932472229004, "timesteps_since_restore": 0, "iterations_since_restore": 30, "warmup_time": 0.020693063735961914}
{"loss": 1.800672069099379, "time_this_iter_s": 0.0039031505584716797, "done": false, "timesteps_total": null, "episodes_total": null, "training_iteration": 31, "trial_id": "ba5ed_00436", "experiment_id": "a082c4a67b3b4881aef6796770906850", "date": "2022-12-09_17-27-07", "timestamp": 1670603227, "time_total_s": 24.08322787284851, "pid": 42084, "hostname": "MacBook-Pro-van-Sicco.local", "node_ip": "127.0.0.1", "config": {"horizon_size": 7, "horizon_list": [1, 2, 3, 4, 5, 6, 12], "quantile_size": 7, "tau_vec": [0.05, 0.1, 0.25, 0.5, 0.75, 0.9, 0.95], "columns": [1], "hidden_size": 12, "context_size": 4, "covariate_size": 3, "p1": 40, "initialization_prior": "Gaussian", "lr": 0.1, "layer_size": 1, "dropout": 0.0, "by_direction": false, "batch_size": 1, "num_epochs": 150, "early_validation_stopping": 8, "val_frac": 0.2, "load_stored_model": true, "store_results": true, "store_model": false, "dir_to_store_reg_quantiles": "s2s_results", "save_nn_name": "s2s_sim_exp2", "M": 10000, "m": 0, "sample_size": 150, "test_size": 200, "date": "221014", "seed": null, "device": "cpu"}, "time_since_restore": 24.08322787284851, "timesteps_since_restore": 0, "iterations_since_restore": 31, "warmup_time": 0.020693063735961914}
{"loss": 1.8069156623034743, "time_this_iter_s": 0.0040318965911865234, "done": false, "timesteps_total": null, "episodes_total": null, "training_iteration": 32, "trial_id": "ba5ed_00436", "experiment_id": "a082c4a67b3b4881aef6796770906850", "date": "2022-12-09_17-27-07", "timestamp": 1670603227, "time_total_s": 24.087259769439697, "pid": 42084, "hostname": "MacBook-Pro-van-Sicco.local", "node_ip": "127.0.0.1", "config": {"horizon_size": 7, "horizon_list": [1, 2, 3, 4, 5, 6, 12], "quantile_size": 7, "tau_vec": [0.05, 0.1, 0.25, 0.5, 0.75, 0.9, 0.95], "columns": [1], "hidden_size": 12, "context_size": 4, "covariate_size": 3, "p1": 40, "initialization_prior": "Gaussian", "lr": 0.1, "layer_size": 1, "dropout": 0.0, "by_direction": false, "batch_size": 1, "num_epochs": 150, "early_validation_stopping": 8, "val_frac": 0.2, "load_stored_model": true, "store_results": true, "store_model": false, "dir_to_store_reg_quantiles": "s2s_results", "save_nn_name": "s2s_sim_exp2", "M": 10000, "m": 0, "sample_size": 150, "test_size": 200, "date": "221014", "seed": null, "device": "cpu"}, "time_since_restore": 24.087259769439697, "timesteps_since_restore": 0, "iterations_since_restore": 32, "warmup_time": 0.020693063735961914}
{"loss": 1.8003854692352483, "time_this_iter_s": 0.004934072494506836, "done": false, "timesteps_total": null, "episodes_total": null, "training_iteration": 33, "trial_id": "ba5ed_00436", "experiment_id": "a082c4a67b3b4881aef6796770906850", "date": "2022-12-09_17-27-07", "timestamp": 1670603227, "time_total_s": 24.092193841934204, "pid": 42084, "hostname": "MacBook-Pro-van-Sicco.local", "node_ip": "127.0.0.1", "config": {"horizon_size": 7, "horizon_list": [1, 2, 3, 4, 5, 6, 12], "quantile_size": 7, "tau_vec": [0.05, 0.1, 0.25, 0.5, 0.75, 0.9, 0.95], "columns": [1], "hidden_size": 12, "context_size": 4, "covariate_size": 3, "p1": 40, "initialization_prior": "Gaussian", "lr": 0.1, "layer_size": 1, "dropout": 0.0, "by_direction": false, "batch_size": 1, "num_epochs": 150, "early_validation_stopping": 8, "val_frac": 0.2, "load_stored_model": true, "store_results": true, "store_model": false, "dir_to_store_reg_quantiles": "s2s_results", "save_nn_name": "s2s_sim_exp2", "M": 10000, "m": 0, "sample_size": 150, "test_size": 200, "date": "221014", "seed": null, "device": "cpu"}, "time_since_restore": 24.092193841934204, "timesteps_since_restore": 0, "iterations_since_restore": 33, "warmup_time": 0.020693063735961914}
{"loss": 1.786888359496312, "time_this_iter_s": 0.006147861480712891, "done": false, "timesteps_total": null, "episodes_total": null, "training_iteration": 34, "trial_id": "ba5ed_00436", "experiment_id": "a082c4a67b3b4881aef6796770906850", "date": "2022-12-09_17-27-07", "timestamp": 1670603227, "time_total_s": 24.098341703414917, "pid": 42084, "hostname": "MacBook-Pro-van-Sicco.local", "node_ip": "127.0.0.1", "config": {"horizon_size": 7, "horizon_list": [1, 2, 3, 4, 5, 6, 12], "quantile_size": 7, "tau_vec": [0.05, 0.1, 0.25, 0.5, 0.75, 0.9, 0.95], "columns": [1], "hidden_size": 12, "context_size": 4, "covariate_size": 3, "p1": 40, "initialization_prior": "Gaussian", "lr": 0.1, "layer_size": 1, "dropout": 0.0, "by_direction": false, "batch_size": 1, "num_epochs": 150, "early_validation_stopping": 8, "val_frac": 0.2, "load_stored_model": true, "store_results": true, "store_model": false, "dir_to_store_reg_quantiles": "s2s_results", "save_nn_name": "s2s_sim_exp2", "M": 10000, "m": 0, "sample_size": 150, "test_size": 200, "date": "221014", "seed": null, "device": "cpu"}, "time_since_restore": 24.098341703414917, "timesteps_since_restore": 0, "iterations_since_restore": 34, "warmup_time": 0.020693063735961914}
{"loss": 1.766307380628882, "time_this_iter_s": 0.005670309066772461, "done": false, "timesteps_total": null, "episodes_total": null, "training_iteration": 35, "trial_id": "ba5ed_00436", "experiment_id": "a082c4a67b3b4881aef6796770906850", "date": "2022-12-09_17-27-07", "timestamp": 1670603227, "time_total_s": 24.10401201248169, "pid": 42084, "hostname": "MacBook-Pro-van-Sicco.local", "node_ip": "127.0.0.1", "config": {"horizon_size": 7, "horizon_list": [1, 2, 3, 4, 5, 6, 12], "quantile_size": 7, "tau_vec": [0.05, 0.1, 0.25, 0.5, 0.75, 0.9, 0.95], "columns": [1], "hidden_size": 12, "context_size": 4, "covariate_size": 3, "p1": 40, "initialization_prior": "Gaussian", "lr": 0.1, "layer_size": 1, "dropout": 0.0, "by_direction": false, "batch_size": 1, "num_epochs": 150, "early_validation_stopping": 8, "val_frac": 0.2, "load_stored_model": true, "store_results": true, "store_model": false, "dir_to_store_reg_quantiles": "s2s_results", "save_nn_name": "s2s_sim_exp2", "M": 10000, "m": 0, "sample_size": 150, "test_size": 200, "date": "221014", "seed": null, "device": "cpu"}, "time_since_restore": 24.10401201248169, "timesteps_since_restore": 0, "iterations_since_restore": 35, "warmup_time": 0.020693063735961914}
{"loss": 1.7500782842221467, "time_this_iter_s": 0.004415988922119141, "done": false, "timesteps_total": null, "episodes_total": null, "training_iteration": 36, "trial_id": "ba5ed_00436", "experiment_id": "a082c4a67b3b4881aef6796770906850", "date": "2022-12-09_17-27-07", "timestamp": 1670603227, "time_total_s": 24.10842800140381, "pid": 42084, "hostname": "MacBook-Pro-van-Sicco.local", "node_ip": "127.0.0.1", "config": {"horizon_size": 7, "horizon_list": [1, 2, 3, 4, 5, 6, 12], "quantile_size": 7, "tau_vec": [0.05, 0.1, 0.25, 0.5, 0.75, 0.9, 0.95], "columns": [1], "hidden_size": 12, "context_size": 4, "covariate_size": 3, "p1": 40, "initialization_prior": "Gaussian", "lr": 0.1, "layer_size": 1, "dropout": 0.0, "by_direction": false, "batch_size": 1, "num_epochs": 150, "early_validation_stopping": 8, "val_frac": 0.2, "load_stored_model": true, "store_results": true, "store_model": false, "dir_to_store_reg_quantiles": "s2s_results", "save_nn_name": "s2s_sim_exp2", "M": 10000, "m": 0, "sample_size": 150, "test_size": 200, "date": "221014", "seed": null, "device": "cpu"}, "time_since_restore": 24.10842800140381, "timesteps_since_restore": 0, "iterations_since_restore": 36, "warmup_time": 0.020693063735961914}
{"loss": 1.7361707983550079, "time_this_iter_s": 0.007460832595825195, "done": false, "timesteps_total": null, "episodes_total": null, "training_iteration": 37, "trial_id": "ba5ed_00436", "experiment_id": "a082c4a67b3b4881aef6796770906850", "date": "2022-12-09_17-27-07", "timestamp": 1670603227, "time_total_s": 24.115888833999634, "pid": 42084, "hostname": "MacBook-Pro-van-Sicco.local", "node_ip": "127.0.0.1", "config": {"horizon_size": 7, "horizon_list": [1, 2, 3, 4, 5, 6, 12], "quantile_size": 7, "tau_vec": [0.05, 0.1, 0.25, 0.5, 0.75, 0.9, 0.95], "columns": [1], "hidden_size": 12, "context_size": 4, "covariate_size": 3, "p1": 40, "initialization_prior": "Gaussian", "lr": 0.1, "layer_size": 1, "dropout": 0.0, "by_direction": false, "batch_size": 1, "num_epochs": 150, "early_validation_stopping": 8, "val_frac": 0.2, "load_stored_model": true, "store_results": true, "store_model": false, "dir_to_store_reg_quantiles": "s2s_results", "save_nn_name": "s2s_sim_exp2", "M": 10000, "m": 0, "sample_size": 150, "test_size": 200, "date": "221014", "seed": null, "device": "cpu"}, "time_since_restore": 24.115888833999634, "timesteps_since_restore": 0, "iterations_since_restore": 37, "warmup_time": 0.020693063735961914}
{"loss": 1.722508590413917, "time_this_iter_s": 0.006140947341918945, "done": false, "timesteps_total": null, "episodes_total": null, "training_iteration": 38, "trial_id": "ba5ed_00436", "experiment_id": "a082c4a67b3b4881aef6796770906850", "date": "2022-12-09_17-27-07", "timestamp": 1670603227, "time_total_s": 24.122029781341553, "pid": 42084, "hostname": "MacBook-Pro-van-Sicco.local", "node_ip": "127.0.0.1", "config": {"horizon_size": 7, "horizon_list": [1, 2, 3, 4, 5, 6, 12], "quantile_size": 7, "tau_vec": [0.05, 0.1, 0.25, 0.5, 0.75, 0.9, 0.95], "columns": [1], "hidden_size": 12, "context_size": 4, "covariate_size": 3, "p1": 40, "initialization_prior": "Gaussian", "lr": 0.1, "layer_size": 1, "dropout": 0.0, "by_direction": false, "batch_size": 1, "num_epochs": 150, "early_validation_stopping": 8, "val_frac": 0.2, "load_stored_model": true, "store_results": true, "store_model": false, "dir_to_store_reg_quantiles": "s2s_results", "save_nn_name": "s2s_sim_exp2", "M": 10000, "m": 0, "sample_size": 150, "test_size": 200, "date": "221014", "seed": null, "device": "cpu"}, "time_since_restore": 24.122029781341553, "timesteps_since_restore": 0, "iterations_since_restore": 38, "warmup_time": 0.020693063735961914}
{"loss": 1.7116159000752136, "time_this_iter_s": 0.005697011947631836, "done": false, "timesteps_total": null, "episodes_total": null, "training_iteration": 39, "trial_id": "ba5ed_00436", "experiment_id": "a082c4a67b3b4881aef6796770906850", "date": "2022-12-09_17-27-07", "timestamp": 1670603227, "time_total_s": 24.127726793289185, "pid": 42084, "hostname": "MacBook-Pro-van-Sicco.local", "node_ip": "127.0.0.1", "config": {"horizon_size": 7, "horizon_list": [1, 2, 3, 4, 5, 6, 12], "quantile_size": 7, "tau_vec": [0.05, 0.1, 0.25, 0.5, 0.75, 0.9, 0.95], "columns": [1], "hidden_size": 12, "context_size": 4, "covariate_size": 3, "p1": 40, "initialization_prior": "Gaussian", "lr": 0.1, "layer_size": 1, "dropout": 0.0, "by_direction": false, "batch_size": 1, "num_epochs": 150, "early_validation_stopping": 8, "val_frac": 0.2, "load_stored_model": true, "store_results": true, "store_model": false, "dir_to_store_reg_quantiles": "s2s_results", "save_nn_name": "s2s_sim_exp2", "M": 10000, "m": 0, "sample_size": 150, "test_size": 200, "date": "221014", "seed": null, "device": "cpu"}, "time_since_restore": 24.127726793289185, "timesteps_since_restore": 0, "iterations_since_restore": 39, "warmup_time": 0.020693063735961914}
{"loss": 1.6937229322350544, "time_this_iter_s": 0.00469207763671875, "done": false, "timesteps_total": null, "episodes_total": null, "training_iteration": 40, "trial_id": "ba5ed_00436", "experiment_id": "a082c4a67b3b4881aef6796770906850", "date": "2022-12-09_17-27-07", "timestamp": 1670603227, "time_total_s": 24.132418870925903, "pid": 42084, "hostname": "MacBook-Pro-van-Sicco.local", "node_ip": "127.0.0.1", "config": {"horizon_size": 7, "horizon_list": [1, 2, 3, 4, 5, 6, 12], "quantile_size": 7, "tau_vec": [0.05, 0.1, 0.25, 0.5, 0.75, 0.9, 0.95], "columns": [1], "hidden_size": 12, "context_size": 4, "covariate_size": 3, "p1": 40, "initialization_prior": "Gaussian", "lr": 0.1, "layer_size": 1, "dropout": 0.0, "by_direction": false, "batch_size": 1, "num_epochs": 150, "early_validation_stopping": 8, "val_frac": 0.2, "load_stored_model": true, "store_results": true, "store_model": false, "dir_to_store_reg_quantiles": "s2s_results", "save_nn_name": "s2s_sim_exp2", "M": 10000, "m": 0, "sample_size": 150, "test_size": 200, "date": "221014", "seed": null, "device": "cpu"}, "time_since_restore": 24.132418870925903, "timesteps_since_restore": 0, "iterations_since_restore": 40, "warmup_time": 0.020693063735961914}
{"loss": 1.6977292647272904, "time_this_iter_s": 0.0053310394287109375, "done": false, "timesteps_total": null, "episodes_total": null, "training_iteration": 41, "trial_id": "ba5ed_00436", "experiment_id": "a082c4a67b3b4881aef6796770906850", "date": "2022-12-09_17-27-07", "timestamp": 1670603227, "time_total_s": 24.137749910354614, "pid": 42084, "hostname": "MacBook-Pro-van-Sicco.local", "node_ip": "127.0.0.1", "config": {"horizon_size": 7, "horizon_list": [1, 2, 3, 4, 5, 6, 12], "quantile_size": 7, "tau_vec": [0.05, 0.1, 0.25, 0.5, 0.75, 0.9, 0.95], "columns": [1], "hidden_size": 12, "context_size": 4, "covariate_size": 3, "p1": 40, "initialization_prior": "Gaussian", "lr": 0.1, "layer_size": 1, "dropout": 0.0, "by_direction": false, "batch_size": 1, "num_epochs": 150, "early_validation_stopping": 8, "val_frac": 0.2, "load_stored_model": true, "store_results": true, "store_model": false, "dir_to_store_reg_quantiles": "s2s_results", "save_nn_name": "s2s_sim_exp2", "M": 10000, "m": 0, "sample_size": 150, "test_size": 200, "date": "221014", "seed": null, "device": "cpu"}, "time_since_restore": 24.137749910354614, "timesteps_since_restore": 0, "iterations_since_restore": 41, "warmup_time": 0.020693063735961914}
{"loss": 1.6783204641401397, "time_this_iter_s": 0.004954814910888672, "done": false, "timesteps_total": null, "episodes_total": null, "training_iteration": 42, "trial_id": "ba5ed_00436", "experiment_id": "a082c4a67b3b4881aef6796770906850", "date": "2022-12-09_17-27-07", "timestamp": 1670603227, "time_total_s": 24.142704725265503, "pid": 42084, "hostname": "MacBook-Pro-van-Sicco.local", "node_ip": "127.0.0.1", "config": {"horizon_size": 7, "horizon_list": [1, 2, 3, 4, 5, 6, 12], "quantile_size": 7, "tau_vec": [0.05, 0.1, 0.25, 0.5, 0.75, 0.9, 0.95], "columns": [1], "hidden_size": 12, "context_size": 4, "covariate_size": 3, "p1": 40, "initialization_prior": "Gaussian", "lr": 0.1, "layer_size": 1, "dropout": 0.0, "by_direction": false, "batch_size": 1, "num_epochs": 150, "early_validation_stopping": 8, "val_frac": 0.2, "load_stored_model": true, "store_results": true, "store_model": false, "dir_to_store_reg_quantiles": "s2s_results", "save_nn_name": "s2s_sim_exp2", "M": 10000, "m": 0, "sample_size": 150, "test_size": 200, "date": "221014", "seed": null, "device": "cpu"}, "time_since_restore": 24.142704725265503, "timesteps_since_restore": 0, "iterations_since_restore": 42, "warmup_time": 0.020693063735961914}
{"loss": 1.677010482882861, "time_this_iter_s": 0.005616188049316406, "done": false, "timesteps_total": null, "episodes_total": null, "training_iteration": 43, "trial_id": "ba5ed_00436", "experiment_id": "a082c4a67b3b4881aef6796770906850", "date": "2022-12-09_17-27-07", "timestamp": 1670603227, "time_total_s": 24.14832091331482, "pid": 42084, "hostname": "MacBook-Pro-van-Sicco.local", "node_ip": "127.0.0.1", "config": {"horizon_size": 7, "horizon_list": [1, 2, 3, 4, 5, 6, 12], "quantile_size": 7, "tau_vec": [0.05, 0.1, 0.25, 0.5, 0.75, 0.9, 0.95], "columns": [1], "hidden_size": 12, "context_size": 4, "covariate_size": 3, "p1": 40, "initialization_prior": "Gaussian", "lr": 0.1, "layer_size": 1, "dropout": 0.0, "by_direction": false, "batch_size": 1, "num_epochs": 150, "early_validation_stopping": 8, "val_frac": 0.2, "load_stored_model": true, "store_results": true, "store_model": false, "dir_to_store_reg_quantiles": "s2s_results", "save_nn_name": "s2s_sim_exp2", "M": 10000, "m": 0, "sample_size": 150, "test_size": 200, "date": "221014", "seed": null, "device": "cpu"}, "time_since_restore": 24.14832091331482, "timesteps_since_restore": 0, "iterations_since_restore": 43, "warmup_time": 0.020693063735961914}
{"loss": 1.6745486052139946, "time_this_iter_s": 0.0047528743743896484, "done": false, "timesteps_total": null, "episodes_total": null, "training_iteration": 44, "trial_id": "ba5ed_00436", "experiment_id": "a082c4a67b3b4881aef6796770906850", "date": "2022-12-09_17-27-07", "timestamp": 1670603227, "time_total_s": 24.15307378768921, "pid": 42084, "hostname": "MacBook-Pro-van-Sicco.local", "node_ip": "127.0.0.1", "config": {"horizon_size": 7, "horizon_list": [1, 2, 3, 4, 5, 6, 12], "quantile_size": 7, "tau_vec": [0.05, 0.1, 0.25, 0.5, 0.75, 0.9, 0.95], "columns": [1], "hidden_size": 12, "context_size": 4, "covariate_size": 3, "p1": 40, "initialization_prior": "Gaussian", "lr": 0.1, "layer_size": 1, "dropout": 0.0, "by_direction": false, "batch_size": 1, "num_epochs": 150, "early_validation_stopping": 8, "val_frac": 0.2, "load_stored_model": true, "store_results": true, "store_model": false, "dir_to_store_reg_quantiles": "s2s_results", "save_nn_name": "s2s_sim_exp2", "M": 10000, "m": 0, "sample_size": 150, "test_size": 200, "date": "221014", "seed": null, "device": "cpu"}, "time_since_restore": 24.15307378768921, "timesteps_since_restore": 0, "iterations_since_restore": 44, "warmup_time": 0.020693063735961914}
{"loss": 1.6734730975228067, "time_this_iter_s": 0.00495600700378418, "done": false, "timesteps_total": null, "episodes_total": null, "training_iteration": 45, "trial_id": "ba5ed_00436", "experiment_id": "a082c4a67b3b4881aef6796770906850", "date": "2022-12-09_17-27-07", "timestamp": 1670603227, "time_total_s": 24.158029794692993, "pid": 42084, "hostname": "MacBook-Pro-van-Sicco.local", "node_ip": "127.0.0.1", "config": {"horizon_size": 7, "horizon_list": [1, 2, 3, 4, 5, 6, 12], "quantile_size": 7, "tau_vec": [0.05, 0.1, 0.25, 0.5, 0.75, 0.9, 0.95], "columns": [1], "hidden_size": 12, "context_size": 4, "covariate_size": 3, "p1": 40, "initialization_prior": "Gaussian", "lr": 0.1, "layer_size": 1, "dropout": 0.0, "by_direction": false, "batch_size": 1, "num_epochs": 150, "early_validation_stopping": 8, "val_frac": 0.2, "load_stored_model": true, "store_results": true, "store_model": false, "dir_to_store_reg_quantiles": "s2s_results", "save_nn_name": "s2s_sim_exp2", "M": 10000, "m": 0, "sample_size": 150, "test_size": 200, "date": "221014", "seed": null, "device": "cpu"}, "time_since_restore": 24.158029794692993, "timesteps_since_restore": 0, "iterations_since_restore": 45, "warmup_time": 0.020693063735961914}
{"loss": 1.670850860406153, "time_this_iter_s": 0.005053043365478516, "done": false, "timesteps_total": null, "episodes_total": null, "training_iteration": 46, "trial_id": "ba5ed_00436", "experiment_id": "a082c4a67b3b4881aef6796770906850", "date": "2022-12-09_17-27-07", "timestamp": 1670603227, "time_total_s": 24.16308283805847, "pid": 42084, "hostname": "MacBook-Pro-van-Sicco.local", "node_ip": "127.0.0.1", "config": {"horizon_size": 7, "horizon_list": [1, 2, 3, 4, 5, 6, 12], "quantile_size": 7, "tau_vec": [0.05, 0.1, 0.25, 0.5, 0.75, 0.9, 0.95], "columns": [1], "hidden_size": 12, "context_size": 4, "covariate_size": 3, "p1": 40, "initialization_prior": "Gaussian", "lr": 0.1, "layer_size": 1, "dropout": 0.0, "by_direction": false, "batch_size": 1, "num_epochs": 150, "early_validation_stopping": 8, "val_frac": 0.2, "load_stored_model": true, "store_results": true, "store_model": false, "dir_to_store_reg_quantiles": "s2s_results", "save_nn_name": "s2s_sim_exp2", "M": 10000, "m": 0, "sample_size": 150, "test_size": 200, "date": "221014", "seed": null, "device": "cpu"}, "time_since_restore": 24.16308283805847, "timesteps_since_restore": 0, "iterations_since_restore": 46, "warmup_time": 0.020693063735961914}
{"loss": 1.6717701787533967, "time_this_iter_s": 0.004476070404052734, "done": false, "timesteps_total": null, "episodes_total": null, "training_iteration": 47, "trial_id": "ba5ed_00436", "experiment_id": "a082c4a67b3b4881aef6796770906850", "date": "2022-12-09_17-27-07", "timestamp": 1670603227, "time_total_s": 24.167558908462524, "pid": 42084, "hostname": "MacBook-Pro-van-Sicco.local", "node_ip": "127.0.0.1", "config": {"horizon_size": 7, "horizon_list": [1, 2, 3, 4, 5, 6, 12], "quantile_size": 7, "tau_vec": [0.05, 0.1, 0.25, 0.5, 0.75, 0.9, 0.95], "columns": [1], "hidden_size": 12, "context_size": 4, "covariate_size": 3, "p1": 40, "initialization_prior": "Gaussian", "lr": 0.1, "layer_size": 1, "dropout": 0.0, "by_direction": false, "batch_size": 1, "num_epochs": 150, "early_validation_stopping": 8, "val_frac": 0.2, "load_stored_model": true, "store_results": true, "store_model": false, "dir_to_store_reg_quantiles": "s2s_results", "save_nn_name": "s2s_sim_exp2", "M": 10000, "m": 0, "sample_size": 150, "test_size": 200, "date": "221014", "seed": null, "device": "cpu"}, "time_since_restore": 24.167558908462524, "timesteps_since_restore": 0, "iterations_since_restore": 47, "warmup_time": 0.020693063735961914}
{"loss": 1.6663590899165373, "time_this_iter_s": 0.005127906799316406, "done": false, "timesteps_total": null, "episodes_total": null, "training_iteration": 48, "trial_id": "ba5ed_00436", "experiment_id": "a082c4a67b3b4881aef6796770906850", "date": "2022-12-09_17-27-07", "timestamp": 1670603227, "time_total_s": 24.17268681526184, "pid": 42084, "hostname": "MacBook-Pro-van-Sicco.local", "node_ip": "127.0.0.1", "config": {"horizon_size": 7, "horizon_list": [1, 2, 3, 4, 5, 6, 12], "quantile_size": 7, "tau_vec": [0.05, 0.1, 0.25, 0.5, 0.75, 0.9, 0.95], "columns": [1], "hidden_size": 12, "context_size": 4, "covariate_size": 3, "p1": 40, "initialization_prior": "Gaussian", "lr": 0.1, "layer_size": 1, "dropout": 0.0, "by_direction": false, "batch_size": 1, "num_epochs": 150, "early_validation_stopping": 8, "val_frac": 0.2, "load_stored_model": true, "store_results": true, "store_model": false, "dir_to_store_reg_quantiles": "s2s_results", "save_nn_name": "s2s_sim_exp2", "M": 10000, "m": 0, "sample_size": 150, "test_size": 200, "date": "221014", "seed": null, "device": "cpu"}, "time_since_restore": 24.17268681526184, "timesteps_since_restore": 0, "iterations_since_restore": 48, "warmup_time": 0.020693063735961914}
{"loss": 1.6652820658239518, "time_this_iter_s": 0.0037679672241210938, "done": false, "timesteps_total": null, "episodes_total": null, "training_iteration": 49, "trial_id": "ba5ed_00436", "experiment_id": "a082c4a67b3b4881aef6796770906850", "date": "2022-12-09_17-27-07", "timestamp": 1670603227, "time_total_s": 24.176454782485962, "pid": 42084, "hostname": "MacBook-Pro-van-Sicco.local", "node_ip": "127.0.0.1", "config": {"horizon_size": 7, "horizon_list": [1, 2, 3, 4, 5, 6, 12], "quantile_size": 7, "tau_vec": [0.05, 0.1, 0.25, 0.5, 0.75, 0.9, 0.95], "columns": [1], "hidden_size": 12, "context_size": 4, "covariate_size": 3, "p1": 40, "initialization_prior": "Gaussian", "lr": 0.1, "layer_size": 1, "dropout": 0.0, "by_direction": false, "batch_size": 1, "num_epochs": 150, "early_validation_stopping": 8, "val_frac": 0.2, "load_stored_model": true, "store_results": true, "store_model": false, "dir_to_store_reg_quantiles": "s2s_results", "save_nn_name": "s2s_sim_exp2", "M": 10000, "m": 0, "sample_size": 150, "test_size": 200, "date": "221014", "seed": null, "device": "cpu"}, "time_since_restore": 24.176454782485962, "timesteps_since_restore": 0, "iterations_since_restore": 49, "warmup_time": 0.020693063735961914}
{"loss": 1.6631881050441577, "time_this_iter_s": 0.005268096923828125, "done": false, "timesteps_total": null, "episodes_total": null, "training_iteration": 50, "trial_id": "ba5ed_00436", "experiment_id": "a082c4a67b3b4881aef6796770906850", "date": "2022-12-09_17-27-07", "timestamp": 1670603227, "time_total_s": 24.18172287940979, "pid": 42084, "hostname": "MacBook-Pro-van-Sicco.local", "node_ip": "127.0.0.1", "config": {"horizon_size": 7, "horizon_list": [1, 2, 3, 4, 5, 6, 12], "quantile_size": 7, "tau_vec": [0.05, 0.1, 0.25, 0.5, 0.75, 0.9, 0.95], "columns": [1], "hidden_size": 12, "context_size": 4, "covariate_size": 3, "p1": 40, "initialization_prior": "Gaussian", "lr": 0.1, "layer_size": 1, "dropout": 0.0, "by_direction": false, "batch_size": 1, "num_epochs": 150, "early_validation_stopping": 8, "val_frac": 0.2, "load_stored_model": true, "store_results": true, "store_model": false, "dir_to_store_reg_quantiles": "s2s_results", "save_nn_name": "s2s_sim_exp2", "M": 10000, "m": 0, "sample_size": 150, "test_size": 200, "date": "221014", "seed": null, "device": "cpu"}, "time_since_restore": 24.18172287940979, "timesteps_since_restore": 0, "iterations_since_restore": 50, "warmup_time": 0.020693063735961914}
{"loss": 1.659162059333754, "time_this_iter_s": 0.00466609001159668, "done": false, "timesteps_total": null, "episodes_total": null, "training_iteration": 51, "trial_id": "ba5ed_00436", "experiment_id": "a082c4a67b3b4881aef6796770906850", "date": "2022-12-09_17-27-07", "timestamp": 1670603227, "time_total_s": 24.186388969421387, "pid": 42084, "hostname": "MacBook-Pro-van-Sicco.local", "node_ip": "127.0.0.1", "config": {"horizon_size": 7, "horizon_list": [1, 2, 3, 4, 5, 6, 12], "quantile_size": 7, "tau_vec": [0.05, 0.1, 0.25, 0.5, 0.75, 0.9, 0.95], "columns": [1], "hidden_size": 12, "context_size": 4, "covariate_size": 3, "p1": 40, "initialization_prior": "Gaussian", "lr": 0.1, "layer_size": 1, "dropout": 0.0, "by_direction": false, "batch_size": 1, "num_epochs": 150, "early_validation_stopping": 8, "val_frac": 0.2, "load_stored_model": true, "store_results": true, "store_model": false, "dir_to_store_reg_quantiles": "s2s_results", "save_nn_name": "s2s_sim_exp2", "M": 10000, "m": 0, "sample_size": 150, "test_size": 200, "date": "221014", "seed": null, "device": "cpu"}, "time_since_restore": 24.186388969421387, "timesteps_since_restore": 0, "iterations_since_restore": 51, "warmup_time": 0.020693063735961914}
{"loss": 1.6580037182162266, "time_this_iter_s": 0.004744768142700195, "done": false, "timesteps_total": null, "episodes_total": null, "training_iteration": 52, "trial_id": "ba5ed_00436", "experiment_id": "a082c4a67b3b4881aef6796770906850", "date": "2022-12-09_17-27-07", "timestamp": 1670603227, "time_total_s": 24.191133737564087, "pid": 42084, "hostname": "MacBook-Pro-van-Sicco.local", "node_ip": "127.0.0.1", "config": {"horizon_size": 7, "horizon_list": [1, 2, 3, 4, 5, 6, 12], "quantile_size": 7, "tau_vec": [0.05, 0.1, 0.25, 0.5, 0.75, 0.9, 0.95], "columns": [1], "hidden_size": 12, "context_size": 4, "covariate_size": 3, "p1": 40, "initialization_prior": "Gaussian", "lr": 0.1, "layer_size": 1, "dropout": 0.0, "by_direction": false, "batch_size": 1, "num_epochs": 150, "early_validation_stopping": 8, "val_frac": 0.2, "load_stored_model": true, "store_results": true, "store_model": false, "dir_to_store_reg_quantiles": "s2s_results", "save_nn_name": "s2s_sim_exp2", "M": 10000, "m": 0, "sample_size": 150, "test_size": 200, "date": "221014", "seed": null, "device": "cpu"}, "time_since_restore": 24.191133737564087, "timesteps_since_restore": 0, "iterations_since_restore": 52, "warmup_time": 0.020693063735961914}
{"loss": 1.6580869307429154, "time_this_iter_s": 0.005292177200317383, "done": false, "timesteps_total": null, "episodes_total": null, "training_iteration": 53, "trial_id": "ba5ed_00436", "experiment_id": "a082c4a67b3b4881aef6796770906850", "date": "2022-12-09_17-27-07", "timestamp": 1670603227, "time_total_s": 24.196425914764404, "pid": 42084, "hostname": "MacBook-Pro-van-Sicco.local", "node_ip": "127.0.0.1", "config": {"horizon_size": 7, "horizon_list": [1, 2, 3, 4, 5, 6, 12], "quantile_size": 7, "tau_vec": [0.05, 0.1, 0.25, 0.5, 0.75, 0.9, 0.95], "columns": [1], "hidden_size": 12, "context_size": 4, "covariate_size": 3, "p1": 40, "initialization_prior": "Gaussian", "lr": 0.1, "layer_size": 1, "dropout": 0.0, "by_direction": false, "batch_size": 1, "num_epochs": 150, "early_validation_stopping": 8, "val_frac": 0.2, "load_stored_model": true, "store_results": true, "store_model": false, "dir_to_store_reg_quantiles": "s2s_results", "save_nn_name": "s2s_sim_exp2", "M": 10000, "m": 0, "sample_size": 150, "test_size": 200, "date": "221014", "seed": null, "device": "cpu"}, "time_since_restore": 24.196425914764404, "timesteps_since_restore": 0, "iterations_since_restore": 53, "warmup_time": 0.020693063735961914}
{"loss": 1.6555573836616848, "time_this_iter_s": 0.004637956619262695, "done": false, "timesteps_total": null, "episodes_total": null, "training_iteration": 54, "trial_id": "ba5ed_00436", "experiment_id": "a082c4a67b3b4881aef6796770906850", "date": "2022-12-09_17-27-07", "timestamp": 1670603227, "time_total_s": 24.201063871383667, "pid": 42084, "hostname": "MacBook-Pro-van-Sicco.local", "node_ip": "127.0.0.1", "config": {"horizon_size": 7, "horizon_list": [1, 2, 3, 4, 5, 6, 12], "quantile_size": 7, "tau_vec": [0.05, 0.1, 0.25, 0.5, 0.75, 0.9, 0.95], "columns": [1], "hidden_size": 12, "context_size": 4, "covariate_size": 3, "p1": 40, "initialization_prior": "Gaussian", "lr": 0.1, "layer_size": 1, "dropout": 0.0, "by_direction": false, "batch_size": 1, "num_epochs": 150, "early_validation_stopping": 8, "val_frac": 0.2, "load_stored_model": true, "store_results": true, "store_model": false, "dir_to_store_reg_quantiles": "s2s_results", "save_nn_name": "s2s_sim_exp2", "M": 10000, "m": 0, "sample_size": 150, "test_size": 200, "date": "221014", "seed": null, "device": "cpu"}, "time_since_restore": 24.201063871383667, "timesteps_since_restore": 0, "iterations_since_restore": 54, "warmup_time": 0.020693063735961914}
{"loss": 1.660750110697302, "time_this_iter_s": 0.0047338008880615234, "done": false, "timesteps_total": null, "episodes_total": null, "training_iteration": 55, "trial_id": "ba5ed_00436", "experiment_id": "a082c4a67b3b4881aef6796770906850", "date": "2022-12-09_17-27-07", "timestamp": 1670603227, "time_total_s": 24.20579767227173, "pid": 42084, "hostname": "MacBook-Pro-van-Sicco.local", "node_ip": "127.0.0.1", "config": {"horizon_size": 7, "horizon_list": [1, 2, 3, 4, 5, 6, 12], "quantile_size": 7, "tau_vec": [0.05, 0.1, 0.25, 0.5, 0.75, 0.9, 0.95], "columns": [1], "hidden_size": 12, "context_size": 4, "covariate_size": 3, "p1": 40, "initialization_prior": "Gaussian", "lr": 0.1, "layer_size": 1, "dropout": 0.0, "by_direction": false, "batch_size": 1, "num_epochs": 150, "early_validation_stopping": 8, "val_frac": 0.2, "load_stored_model": true, "store_results": true, "store_model": false, "dir_to_store_reg_quantiles": "s2s_results", "save_nn_name": "s2s_sim_exp2", "M": 10000, "m": 0, "sample_size": 150, "test_size": 200, "date": "221014", "seed": null, "device": "cpu"}, "time_since_restore": 24.20579767227173, "timesteps_since_restore": 0, "iterations_since_restore": 55, "warmup_time": 0.020693063735961914}
{"loss": 1.6737102247913431, "time_this_iter_s": 0.004666328430175781, "done": false, "timesteps_total": null, "episodes_total": null, "training_iteration": 56, "trial_id": "ba5ed_00436", "experiment_id": "a082c4a67b3b4881aef6796770906850", "date": "2022-12-09_17-27-07", "timestamp": 1670603227, "time_total_s": 24.210464000701904, "pid": 42084, "hostname": "MacBook-Pro-van-Sicco.local", "node_ip": "127.0.0.1", "config": {"horizon_size": 7, "horizon_list": [1, 2, 3, 4, 5, 6, 12], "quantile_size": 7, "tau_vec": [0.05, 0.1, 0.25, 0.5, 0.75, 0.9, 0.95], "columns": [1], "hidden_size": 12, "context_size": 4, "covariate_size": 3, "p1": 40, "initialization_prior": "Gaussian", "lr": 0.1, "layer_size": 1, "dropout": 0.0, "by_direction": false, "batch_size": 1, "num_epochs": 150, "early_validation_stopping": 8, "val_frac": 0.2, "load_stored_model": true, "store_results": true, "store_model": false, "dir_to_store_reg_quantiles": "s2s_results", "save_nn_name": "s2s_sim_exp2", "M": 10000, "m": 0, "sample_size": 150, "test_size": 200, "date": "221014", "seed": null, "device": "cpu"}, "time_since_restore": 24.210464000701904, "timesteps_since_restore": 0, "iterations_since_restore": 56, "warmup_time": 0.020693063735961914}
{"loss": 1.6623355083584046, "time_this_iter_s": 0.0054128170013427734, "done": false, "timesteps_total": null, "episodes_total": null, "training_iteration": 57, "trial_id": "ba5ed_00436", "experiment_id": "a082c4a67b3b4881aef6796770906850", "date": "2022-12-09_17-27-07", "timestamp": 1670603227, "time_total_s": 24.215876817703247, "pid": 42084, "hostname": "MacBook-Pro-van-Sicco.local", "node_ip": "127.0.0.1", "config": {"horizon_size": 7, "horizon_list": [1, 2, 3, 4, 5, 6, 12], "quantile_size": 7, "tau_vec": [0.05, 0.1, 0.25, 0.5, 0.75, 0.9, 0.95], "columns": [1], "hidden_size": 12, "context_size": 4, "covariate_size": 3, "p1": 40, "initialization_prior": "Gaussian", "lr": 0.1, "layer_size": 1, "dropout": 0.0, "by_direction": false, "batch_size": 1, "num_epochs": 150, "early_validation_stopping": 8, "val_frac": 0.2, "load_stored_model": true, "store_results": true, "store_model": false, "dir_to_store_reg_quantiles": "s2s_results", "save_nn_name": "s2s_sim_exp2", "M": 10000, "m": 0, "sample_size": 150, "test_size": 200, "date": "221014", "seed": null, "device": "cpu"}, "time_since_restore": 24.215876817703247, "timesteps_since_restore": 0, "iterations_since_restore": 57, "warmup_time": 0.020693063735961914}
{"loss": 1.660788589382764, "time_this_iter_s": 0.004476070404052734, "done": false, "timesteps_total": null, "episodes_total": null, "training_iteration": 58, "trial_id": "ba5ed_00436", "experiment_id": "a082c4a67b3b4881aef6796770906850", "date": "2022-12-09_17-27-07", "timestamp": 1670603227, "time_total_s": 24.2203528881073, "pid": 42084, "hostname": "MacBook-Pro-van-Sicco.local", "node_ip": "127.0.0.1", "config": {"horizon_size": 7, "horizon_list": [1, 2, 3, 4, 5, 6, 12], "quantile_size": 7, "tau_vec": [0.05, 0.1, 0.25, 0.5, 0.75, 0.9, 0.95], "columns": [1], "hidden_size": 12, "context_size": 4, "covariate_size": 3, "p1": 40, "initialization_prior": "Gaussian", "lr": 0.1, "layer_size": 1, "dropout": 0.0, "by_direction": false, "batch_size": 1, "num_epochs": 150, "early_validation_stopping": 8, "val_frac": 0.2, "load_stored_model": true, "store_results": true, "store_model": false, "dir_to_store_reg_quantiles": "s2s_results", "save_nn_name": "s2s_sim_exp2", "M": 10000, "m": 0, "sample_size": 150, "test_size": 200, "date": "221014", "seed": null, "device": "cpu"}, "time_since_restore": 24.2203528881073, "timesteps_since_restore": 0, "iterations_since_restore": 58, "warmup_time": 0.020693063735961914}
{"loss": 1.6687343431555706, "time_this_iter_s": 0.004817962646484375, "done": false, "timesteps_total": null, "episodes_total": null, "training_iteration": 59, "trial_id": "ba5ed_00436", "experiment_id": "a082c4a67b3b4881aef6796770906850", "date": "2022-12-09_17-27-07", "timestamp": 1670603227, "time_total_s": 24.225170850753784, "pid": 42084, "hostname": "MacBook-Pro-van-Sicco.local", "node_ip": "127.0.0.1", "config": {"horizon_size": 7, "horizon_list": [1, 2, 3, 4, 5, 6, 12], "quantile_size": 7, "tau_vec": [0.05, 0.1, 0.25, 0.5, 0.75, 0.9, 0.95], "columns": [1], "hidden_size": 12, "context_size": 4, "covariate_size": 3, "p1": 40, "initialization_prior": "Gaussian", "lr": 0.1, "layer_size": 1, "dropout": 0.0, "by_direction": false, "batch_size": 1, "num_epochs": 150, "early_validation_stopping": 8, "val_frac": 0.2, "load_stored_model": true, "store_results": true, "store_model": false, "dir_to_store_reg_quantiles": "s2s_results", "save_nn_name": "s2s_sim_exp2", "M": 10000, "m": 0, "sample_size": 150, "test_size": 200, "date": "221014", "seed": null, "device": "cpu"}, "time_since_restore": 24.225170850753784, "timesteps_since_restore": 0, "iterations_since_restore": 59, "warmup_time": 0.020693063735961914}
{"loss": 1.6775218892541732, "time_this_iter_s": 0.005408048629760742, "done": false, "timesteps_total": null, "episodes_total": null, "training_iteration": 60, "trial_id": "ba5ed_00436", "experiment_id": "a082c4a67b3b4881aef6796770906850", "date": "2022-12-09_17-27-07", "timestamp": 1670603227, "time_total_s": 24.230578899383545, "pid": 42084, "hostname": "MacBook-Pro-van-Sicco.local", "node_ip": "127.0.0.1", "config": {"horizon_size": 7, "horizon_list": [1, 2, 3, 4, 5, 6, 12], "quantile_size": 7, "tau_vec": [0.05, 0.1, 0.25, 0.5, 0.75, 0.9, 0.95], "columns": [1], "hidden_size": 12, "context_size": 4, "covariate_size": 3, "p1": 40, "initialization_prior": "Gaussian", "lr": 0.1, "layer_size": 1, "dropout": 0.0, "by_direction": false, "batch_size": 1, "num_epochs": 150, "early_validation_stopping": 8, "val_frac": 0.2, "load_stored_model": true, "store_results": true, "store_model": false, "dir_to_store_reg_quantiles": "s2s_results", "save_nn_name": "s2s_sim_exp2", "M": 10000, "m": 0, "sample_size": 150, "test_size": 200, "date": "221014", "seed": null, "device": "cpu"}, "time_since_restore": 24.230578899383545, "timesteps_since_restore": 0, "iterations_since_restore": 60, "warmup_time": 0.020693063735961914}
{"loss": 1.6695234405328028, "time_this_iter_s": 0.005822896957397461, "done": false, "timesteps_total": null, "episodes_total": null, "training_iteration": 61, "trial_id": "ba5ed_00436", "experiment_id": "a082c4a67b3b4881aef6796770906850", "date": "2022-12-09_17-27-07", "timestamp": 1670603227, "time_total_s": 24.236401796340942, "pid": 42084, "hostname": "MacBook-Pro-van-Sicco.local", "node_ip": "127.0.0.1", "config": {"horizon_size": 7, "horizon_list": [1, 2, 3, 4, 5, 6, 12], "quantile_size": 7, "tau_vec": [0.05, 0.1, 0.25, 0.5, 0.75, 0.9, 0.95], "columns": [1], "hidden_size": 12, "context_size": 4, "covariate_size": 3, "p1": 40, "initialization_prior": "Gaussian", "lr": 0.1, "layer_size": 1, "dropout": 0.0, "by_direction": false, "batch_size": 1, "num_epochs": 150, "early_validation_stopping": 8, "val_frac": 0.2, "load_stored_model": true, "store_results": true, "store_model": false, "dir_to_store_reg_quantiles": "s2s_results", "save_nn_name": "s2s_sim_exp2", "M": 10000, "m": 0, "sample_size": 150, "test_size": 200, "date": "221014", "seed": null, "device": "cpu"}, "time_since_restore": 24.236401796340942, "timesteps_since_restore": 0, "iterations_since_restore": 61, "warmup_time": 0.020693063735961914}
{"loss": 1.6598783694439052, "time_this_iter_s": 0.004781007766723633, "done": false, "timesteps_total": null, "episodes_total": null, "training_iteration": 62, "trial_id": "ba5ed_00436", "experiment_id": "a082c4a67b3b4881aef6796770906850", "date": "2022-12-09_17-27-07", "timestamp": 1670603227, "time_total_s": 24.241182804107666, "pid": 42084, "hostname": "MacBook-Pro-van-Sicco.local", "node_ip": "127.0.0.1", "config": {"horizon_size": 7, "horizon_list": [1, 2, 3, 4, 5, 6, 12], "quantile_size": 7, "tau_vec": [0.05, 0.1, 0.25, 0.5, 0.75, 0.9, 0.95], "columns": [1], "hidden_size": 12, "context_size": 4, "covariate_size": 3, "p1": 40, "initialization_prior": "Gaussian", "lr": 0.1, "layer_size": 1, "dropout": 0.0, "by_direction": false, "batch_size": 1, "num_epochs": 150, "early_validation_stopping": 8, "val_frac": 0.2, "load_stored_model": true, "store_results": true, "store_model": false, "dir_to_store_reg_quantiles": "s2s_results", "save_nn_name": "s2s_sim_exp2", "M": 10000, "m": 0, "sample_size": 150, "test_size": 200, "date": "221014", "seed": null, "device": "cpu"}, "time_since_restore": 24.241182804107666, "timesteps_since_restore": 0, "iterations_since_restore": 62, "warmup_time": 0.020693063735961914}
